curly.py
setup.py
curly.egg-info/PKG-INFO
curly.egg-info/SOURCES.txt
curly.egg-info/dependency_links.txt
curly.egg-info/top_level.txt