Metadata-Version: 1.0
Name: curly
Version: 0.0.4
Summary: Use the full power of the curl command line easily from Python.
Home-page: https://github.com/zacharyvoase/curly
Author: Zack Voase
Author-email: z@zacharyvoase.com
License: Unlicense
Platform: UNKNOWN
